Decoder/decodificador.v
module decodificador(A,S);

    input [3:0] A;
    output reg [7:0] S;

    always @ (A) begin
        case(A)
        4'b0000: S = 8'b00000001;
        4'b0001: S = 8'b00000010;
        4'b0010: S = 8'b00000100;
        4'b0011: S = 8'b00001000;
        4'b0100: S = 8'b00010000;
        4'b0101: S = 8'b00100000;
        4'b0110: S = 8'b01000000;
        4'b0111: S = 8'b10000000;

        endcase
    end
endmodule

Decoder/decodificador_tb.v
`timescale 1ns/1ps
`include "decodificador.v"

module decodificador_tb;

    reg [3:0] A;
    wire [7:0] S;
    decodificador uut(A, S);

    initial begin
        $dumpfile("decodificador_tb.vcd");
        $dumpvars(0, decodificador_tb);

        A = 4'b0000; #20;
        A = 4'b0001; #20;
        A = 4'b0010; #20;
        A = 4'b0011; #20;
        A = 4'b0100; #20;
        A = 4'b0101; #20;
        A = 4'b0110; #20;
        A = 4'b0111; #20;

        $display("Teste Completo");
    end
endmodule

Decoder/decodificador_tb.vcd
$date
	Mon Sep 23 10:06:44 2024
$end
$version
	Icarus Verilog
$end
$timescale
	1ps
$end
$scope module decodificador_tb $end
$var wire 8 ! S [7:0] $end
$var reg 4 " A [3:0] $end
$scope module uut $end
$var wire 4 # A [3:0] $end
$var reg 8 $ S [7:0] $end
$upscope $end
$upscope $end
$enddefinitions $end
$comment Show the parameter values. $end
$dumpall
$end
#0
$dumpvars
b1 $
b0 #
b0 "
b1 !
$end
#20000
b10 !
b10 $
b1 "
b1 #
#40000
b100 !
b100 $
b10 "
b10 #
#60000
b1000 !
b1000 $
b11 "
b11 #
#80000
b10000 !
b10000 $
b100 "
b100 #
#100000
b100000 !
b100000 $
b101 "
b101 #
#120000
b1000000 !
b1000000 $
b110 "
b110 #
#140000
b10000000 !
b10000000 $
b111 "
b111 #
